{
    "action_inputs": [
        {
            "allow_multiple": false,
            "available_all_servers": false,
            "description": null,
            "field_dependency_controlling_set": [],
            "field_dependency_dependent_set": [],
            "global_options": [],
            "hide_if_default_value": false,
            "label": "Availability Zone",
            "name": "availability_zone",
            "placeholder": null,
            "relevant_osfamilies": [],
            "required": true,
            "show_as_attribute": false,
            "show_on_servers": false,
            "type": "STR",
            "value_pattern_string": null
        },
        {
            "allow_multiple": false,
            "available_all_servers": false,
            "description": null,
            "field_dependency_controlling_set": [],
            "field_dependency_dependent_set": [],
            "global_options": [],
            "hide_if_default_value": false,
            "label": "Cloudbolt Environment",
            "name": "cloudbolt_environment",
            "placeholder": null,
            "relevant_osfamilies": [],
            "required": true,
            "show_as_attribute": false,
            "show_on_servers": false,
            "type": "STR",
            "value_pattern_string": null
        },
        {
            "allow_multiple": false,
            "available_all_servers": false,
            "description": null,
            "field_dependency_controlling_set": [],
            "field_dependency_dependent_set": [],
            "global_options": [],
            "hide_if_default_value": false,
            "label": "Flavor",
            "name": "flavor",
            "placeholder": null,
            "relevant_osfamilies": [],
            "required": true,
            "show_as_attribute": false,
            "show_on_servers": false,
            "type": "STR",
            "value_pattern_string": null
        },
        {
            "allow_multiple": false,
            "available_all_servers": false,
            "description": null,
            "field_dependency_controlling_set": [],
            "field_dependency_dependent_set": [],
            "global_options": [],
            "hide_if_default_value": false,
            "label": "Floating Ips",
            "name": "floating_ips",
            "placeholder": null,
            "relevant_osfamilies": [],
            "required": true,
            "show_as_attribute": false,
            "show_on_servers": false,
            "type": "STR",
            "value_pattern_string": null
        },
        {
            "allow_multiple": false,
            "available_all_servers": false,
            "description": null,
            "field_dependency_controlling_set": [],
            "field_dependency_dependent_set": [],
            "global_options": [],
            "hide_if_default_value": false,
            "label": "Hostname",
            "name": "hostname",
            "placeholder": null,
            "relevant_osfamilies": [],
            "required": true,
            "show_as_attribute": false,
            "show_on_servers": false,
            "type": "STR",
            "value_pattern_string": null
        },
        {
            "allow_multiple": false,
            "available_all_servers": false,
            "description": null,
            "field_dependency_controlling_set": [],
            "field_dependency_dependent_set": [],
            "global_options": [],
            "hide_if_default_value": false,
            "label": "Key Pair Name",
            "name": "key_pair_name",
            "placeholder": null,
            "relevant_osfamilies": [],
            "required": true,
            "show_as_attribute": false,
            "show_on_servers": false,
            "type": "STR",
            "value_pattern_string": null
        },
        {
            "allow_multiple": false,
            "available_all_servers": false,
            "description": null,
            "field_dependency_controlling_set": [],
            "field_dependency_dependent_set": [],
            "global_options": [],
            "hide_if_default_value": false,
            "label": "Network",
            "name": "network",
            "placeholder": null,
            "relevant_osfamilies": [],
            "required": true,
            "show_as_attribute": false,
            "show_on_servers": false,
            "type": "STR",
            "value_pattern_string": null
        },
        {
            "allow_multiple": false,
            "available_all_servers": false,
            "description": null,
            "field_dependency_controlling_set": [],
            "field_dependency_dependent_set": [],
            "global_options": [],
            "hide_if_default_value": false,
            "label": "Security Group",
            "name": "security_group",
            "placeholder": null,
            "relevant_osfamilies": [],
            "required": true,
            "show_as_attribute": false,
            "show_on_servers": false,
            "type": "STR",
            "value_pattern_string": null
        },
        {
            "allow_multiple": false,
            "available_all_servers": false,
            "description": null,
            "field_dependency_controlling_set": [],
            "field_dependency_dependent_set": [],
            "global_options": [],
            "hide_if_default_value": false,
            "label": "Volume",
            "name": "volume",
            "placeholder": null,
            "relevant_osfamilies": [],
            "required": true,
            "show_as_attribute": false,
            "show_on_servers": false,
            "type": "STR",
            "value_pattern_string": null
        }
    ],
    "description": "",
    "id": "OHK-ouqmdqrt",
    "last_updated": "2023-08-09",
    "max_retries": 0,
    "maximum_version_required": "",
    "minimum_version_required": "8.6",
    "name": "Boot Instance from Volume",
    "resource_technologies": [],
    "script_filename": "Boot Instance from Volume Script.py",
    "shared": false,
    "target_os_families": [],
    "type": "CloudBolt Plug-in"
}