{
    "action_input_default_values": [
        {
            "label": "Desired Capacity",
            "name": "desired_capacity_a443",
            "value": "2"
        },
        {
            "label": "Max Size",
            "name": "max_size_a443",
            "value": "2"
        },
        {
            "label": "Min Size",
            "name": "min_size_a443",
            "value": "2"
        }
    ],
    "action_inputs": [
        {
            "allow-multiple": false,
            "available-all-servers": false,
            "description": "",
            "field-dependency-controlling-set": [],
            "field-dependency-dependent-set": [],
            "global-options": [],
            "hide-if-default-value": false,
            "label": "Desired Capacity",
            "maximum": "50.00",
            "minimum": "2.00",
            "name": "desired_capacity",
            "placeholder": null,
            "relevant-osfamilies": [],
            "required": true,
            "show-as-attribute": false,
            "show-on-servers": false,
            "type": "INT",
            "value-pattern-string": ""
        },
        {
            "allow-multiple": false,
            "available-all-servers": false,
            "description": "",
            "field-dependency-controlling-set": [],
            "field-dependency-dependent-set": [],
            "global-options": [],
            "hide-if-default-value": false,
            "label": "Max Size",
            "maximum": "50.00",
            "minimum": "2.00",
            "name": "max_size",
            "placeholder": null,
            "relevant-osfamilies": [],
            "required": true,
            "show-as-attribute": false,
            "show-on-servers": false,
            "type": "INT",
            "value-pattern-string": ""
        },
        {
            "allow-multiple": false,
            "available-all-servers": false,
            "description": "",
            "field-dependency-controlling-set": [],
            "field-dependency-dependent-set": [],
            "global-options": [],
            "hide-if-default-value": false,
            "label": "Min Size",
            "maximum": "50.00",
            "minimum": "2.00",
            "name": "min_size",
            "placeholder": null,
            "relevant-osfamilies": [],
            "required": true,
            "show-as-attribute": false,
            "show-on-servers": false,
            "type": "INT",
            "value-pattern-string": ""
        },
        {
            "allow-multiple": false,
            "available-all-servers": false,
            "description": "",
            "field-dependency-controlling-set": [],
            "field-dependency-dependent-set": [],
            "global-options": [],
            "hide-if-default-value": false,
            "label": "Old Scaling Configuration",
            "name": "old_scaling_configuration",
            "placeholder": null,
            "relevant-osfamilies": [],
            "required": false,
            "show-as-attribute": false,
            "show-on-servers": false,
            "type": "STR",
            "value-pattern-string": ""
        }
    ],
    "base_action_name": "modify_scaling_configuration",
    "dialog_message": "",
    "enabled": true,
    "extra_classes": "far fa-sun",
    "id": "RSA-wesiuceu",
    "label": "Modify Scaling Configuration",
    "last_updated": "2023-03-03",
    "list_view_visible": true,
    "maximum_version_required": "",
    "minimum_version_required": "8.6",
    "requires_approval": false,
    "submit_button_label": ""
}