{
    "action_inputs": [
        {
            "allow_multiple": false,
            "available_all_servers": false,
            "description": "An optional list of ports to which this rule applies. This field is only applicable for UDP or TCP protocol. Each entry must be either an integer or a range. If not specified, this rule applies to connections through any port.",
            "field_dependency_controlling_set": [],
            "field_dependency_dependent_set": [],
            "global_options": [],
            "hide_if_default_value": false,
            "id": "CF-m2j2qddy",
            "label": "Allowed Ports",
            "name": "allowed_ports",
            "placeholder": null,
            "relevant_osfamilies": [],
            "required": true,
            "show_as_attribute": false,
            "show_on_servers": false,
            "type": "STR",
            "value_pattern_string": null
        },
        {
            "allow_multiple": false,
            "available_all_servers": false,
            "description": "The IP protocol to which this rule applies.",
            "field_dependency_controlling_set": [],
            "field_dependency_dependent_set": [],
            "global_options": [],
            "hide_if_default_value": false,
            "id": "CF-9me2icel",
            "label": "Allowed Protocol",
            "name": "allowed_protocol",
            "placeholder": null,
            "relevant_osfamilies": [],
            "required": true,
            "show_as_attribute": false,
            "show_on_servers": false,
            "type": "STR",
            "value_pattern_string": null
        },
        {
            "allow_multiple": false,
            "available_all_servers": false,
            "description": "Direction of traffic to which this firewall applies.",
            "field_dependency_controlling_set": [],
            "field_dependency_dependent_set": [],
            "global_options": [],
            "hide_if_default_value": false,
            "id": "CF-y11qnrxn",
            "label": "Direction",
            "name": "direction",
            "placeholder": null,
            "relevant_osfamilies": [],
            "required": true,
            "show_as_attribute": false,
            "show_on_servers": false,
            "type": "STR",
            "value_pattern_string": null
        },
        {
            "allow_multiple": false,
            "available_all_servers": false,
            "description": null,
            "field_dependency_controlling_set": [],
            "field_dependency_dependent_set": [],
            "global_options": [],
            "hide_if_default_value": false,
            "id": "CF-w5uqjvfu",
            "label": "Env Id",
            "name": "env_id",
            "placeholder": null,
            "relevant_osfamilies": [],
            "required": true,
            "show_as_attribute": false,
            "show_on_servers": false,
            "type": "STR",
            "value_pattern_string": null
        },
        {
            "allow_multiple": false,
            "available_all_servers": false,
            "description": null,
            "field_dependency_controlling_set": [],
            "field_dependency_dependent_set": [],
            "global_options": [],
            "hide_if_default_value": false,
            "id": "CF-zxf45nxe",
            "label": "Firewall Name",
            "name": "firewall_name",
            "placeholder": null,
            "relevant_osfamilies": [],
            "required": true,
            "show_as_attribute": false,
            "show_on_servers": false,
            "type": "STR",
            "value_pattern_string": null
        },
        {
            "allow_multiple": false,
            "available_all_servers": false,
            "description": "Priority for this rule. This is an integer between 0 and 65535, both inclusive.",
            "field_dependency_controlling_set": [],
            "field_dependency_dependent_set": [],
            "global_options": [],
            "hide_if_default_value": false,
            "id": "CF-4vh800f6",
            "label": "Priority",
            "maximum": "65535.00",
            "name": "priority",
            "placeholder": null,
            "relevant_osfamilies": [],
            "required": true,
            "show_as_attribute": false,
            "show_on_servers": false,
            "type": "INT",
            "value_pattern_string": null
        }
    ],
    "action_inputs_sequence": [
        "env_id",
        "allowed_protocol",
        "direction",
        "priority",
        "firewall_name",
        "allowed_ports"
    ],
    "description": "Deploy a google cloud firewall",
    "id": "OHK-m15uumso",
    "last_updated": "2022-09-28",
    "max_retries": 0,
    "maximum_version_required": "",
    "minimum_version_required": "8.6",
    "name": "Google Cloud Firewall Build",
    "resource_technologies": [
        "Google Compute Engine",
        "Google Cloud Platform"
    ],
    "script_filename": "Google Cloud Firewall Build Script.py",
    "shared": false,
    "target_os_families": [],
    "type": "CloudBolt Plug-in"
}